Workbook

Sheet Units
B3: UNITS
B4: g
B5: kg
B6: oz
B7: lbs
B8: mg
B9: mL
B10: L
B11: fl oz
B12: tsp
B13: tbsp
B14: cup
... B28: slice

Sheet Ingredients
B3: INGREDIENT | C3: SUPPLIER | D3: PACKAGE PRICE | E3: QTY PER PACK | F3: SHIPPING FEE | G3: UNIT | H3: UNIT COST
H4: =IF(E4="","",(D4+F4)/E4)
H5: =IF(E5="","",(D5+F5)/E5)
H6: =IF(E6="","",(D6+F6)/E6)
H7: =IF(E7="","",(D7+F7)/E7)
H8: =IF(E8="","",(D8+F8)/E8)
H9: =IF(E9="","",(D9+F9)/E9)
H10: =IF(E10="","",(D10+F10)/E10)
H11: =IF(E11="","",(D11+F11)/E11)
H12: =IF(E12="","",(D12+F12)/E12)
H13: =IF(E13="","",(D13+F13)/E13)
H14: =IF(E14="","",(D14+F14)/E14)
H15: =IF(E15="","",(D15+F15)/E15)
... H1002: =IF(E1002="","",(D1002+F1002)/E1002)

Sheet Other
B3: ITEM | C3: SUPPLIER | D3: PACKAGE PRICE | E3: QTY PER PACK | F3: SHIPPING FEE | G3: UNIT | H3: UNIT COST
H4: =IF(E4="","",(D4+F4)/E4)
H5: =IF(E5="","",(D5+F5)/E5)
H6: =IF(E6="","",(D6+F6)/E6)
H7: =IF(E7="","",(D7+F7)/E7)
H8: =IF(E8="","",(D8+F8)/E8)
H9: =IF(E9="","",(D9+F9)/E9)
H10: =IF(E10="","",(D10+F10)/E10)
H11: =IF(E11="","",(D11+F11)/E11)
H12: =IF(E12="","",(D12+F12)/E12)
H13: =IF(E13="","",(D13+F13)/E13)
H14: =IF(E14="","",(D14+F14)/E14)
H15: =IF(E15="","",(D15+F15)/E15)
... H1002: =IF(E1002="","",(D1002+F1002)/E1002)

Sheet OPEX
B3: OPERATING EXPENSES (OPEX) | C3: AMOUNT/MONTH
B4: Rent
B5: Salaries (staff)
B6: Electricity
B7: Water
B8: Internet/Phone
B9: POS / Software
B10: Cleaning Supplies
B11: LPG / Cooking Fuel
B12: Permits & Licenses, Monthly Allocation
B13: Repairs & Maintenance
B14: Marketing / Ads
B15: Miscellaneous Expenses
B23: TOTAL MONTHLY OPEX | C23: =SUM(C4:C22) -> 0
B24: CONTINGENCY (5%) | C24: =SUM(C4:C22)*0.1 -> 0
B25: ESTIMATED MONTHLY OPEX | C25: =SUM(C23:C24) -> 0

Sheet Summary
B4: RECIPE | C4: PRICING METHOD | D4: SELLING PRICE | E4: COST/ORDER | F4: GROSS PROFIT/ORDER | G4: EST. ORDERS/MONTH | H4: GROSS SALES/MONTH | I4: GROSS PROFIT/MONTH | AA4: VAT/ORDER | AB4: VAT/MONTH | AC4: NET SALES/MONTH | AD4: COGS/MONTH
D5: =IFERROR(SWITCH(C5,"Fixed Markup",INDIRECT("'"&B5&"'!$Q$16"),"Markup %",INDIRECT("'"&B5&"'!$AB$16"),"Margin %",INDIRECT("'"&B5&"'!$AM$16"),"Manual",INDIRECT("'"&B5&"'!$AX$11"),""),"") | E5: =IFERROR(INDIRECT("'"&B5&"'!$V$7"),"") | F5: =IFERROR(SWITCH(C5,"Fixed Markup",INDIRECT("'"&B5&"'!$P$17"),"Markup %",INDIRECT("'"&B5&"'!$AA$17"),"Margin %",INDIRECT("'"&B5&"'!$AL$17"),"Manual",INDIRECT("'"&B5&"'!$AW$16"),""),"") | H5: =IFERROR(D5*G5,0) -> 0 | I5: =IFERROR(F5*G5,0) -> 0 | AA5: =IFERROR(SWITCH(C5,"Fixed Markup",INDIRECT("'"&B5&"'!$Q$14"),"Markup %",INDIRECT("'"&B5&"'!$AB$14"),"Margin %",INDIRECT("'"&B5&"'!$AM$14"),"Manual",INDIRECT("'"&B5&"'!$AX$14"),""),"") | AB5: =AA5*G5 -> 0 | AC5: =H5-AB5 -> 0 | AD5: =E5*G5 -> 0
D6: =IFERROR(SWITCH(C6,"Fixed Markup",INDIRECT("'"&B6&"'!$Q$16"),"Markup %",INDIRECT("'"&B6&"'!$AB$16"),"Margin %",INDIRECT("'"&B6&"'!$AM$16"),"Manual",INDIRECT("'"&B6&"'!$AX$11"),""),"") | E6: =IFERROR(INDIRECT("'"&B6&"'!$V$7"),"") | F6: =IFERROR(SWITCH(C6,"Fixed Markup",INDIRECT("'"&B6&"'!$P$17"),"Markup %",INDIRECT("'"&B6&"'!$AA$17"),"Margin %",INDIRECT("'"&B6&"'!$AL$17"),"Manual",INDIRECT("'"&B6&"'!$AW$16"),""),"") | H6: =IFERROR(D6*G6,0) -> 0 | I6: =IFERROR(F6*G6,0) -> 0 | L6: MONTHLY PROFIT PROJECTION | AA6: =IFERROR(SWITCH(C6,"Fixed Markup",INDIRECT("'"&B6&"'!$Q$14"),"Markup %",INDIRECT("'"&B6&"'!$AB$14"),"Margin %",INDIRECT("'"&B6&"'!$AM$14"),"Manual",INDIRECT("'"&B6&"'!$AX$14"),""),"") | AB6: =AA6*G6 -> 0 | AC6: =H6-AB6 -> 0 | AD6: =E6*G6 -> 0
D7: =IFERROR(SWITCH(C7,"Fixed Markup",INDIRECT("'"&B7&"'!$Q$16"),"Markup %",INDIRECT("'"&B7&"'!$AB$16"),"Margin %",INDIRECT("'"&B7&"'!$AM$16"),"Manual",INDIRECT("'"&B7&"'!$AX$11"),""),"") | E7: =IFERROR(INDIRECT("'"&B7&"'!$V$7"),"") | F7: =IFERROR(SWITCH(C7,"Fixed Markup",INDIRECT("'"&B7&"'!$P$17"),"Markup %",INDIRECT("'"&B7&"'!$AA$17"),"Margin %",INDIRECT("'"&B7&"'!$AL$17"),"Manual",INDIRECT("'"&B7&"'!$AW$16"),""),"") | H7: =IFERROR(D7*G7,0) -> 0 | I7: =IFERROR(F7*G7,0) -> 0 | AA7: =IFERROR(SWITCH(C7,"Fixed Markup",INDIRECT("'"&B7&"'!$Q$14"),"Markup %",INDIRECT("'"&B7&"'!$AB$14"),"Margin %",INDIRECT("'"&B7&"'!$AM$14"),"Manual",INDIRECT("'"&B7&"'!$AX$14"),""),"") | AB7: =AA7*G7 -> 0 | AC7: =H7-AB7 -> 0 | AD7: =E7*G7 -> 0
D8: =IFERROR(SWITCH(C8,"Fixed Markup",INDIRECT("'"&B8&"'!$Q$16"),"Markup %",INDIRECT("'"&B8&"'!$AB$16"),"Margin %",INDIRECT("'"&B8&"'!$AM$16"),"Manual",INDIRECT("'"&B8&"'!$AX$11"),""),"") | E8: =IFERROR(INDIRECT("'"&B8&"'!$V$7"),"") | F8: =IFERROR(SWITCH(C8,"Fixed Markup",INDIRECT("'"&B8&"'!$P$17"),"Markup %",INDIRECT("'"&B8&"'!$AA$17"),"Margin %",INDIRECT("'"&B8&"'!$AL$17"),"Manual",INDIRECT("'"&B8&"'!$AW$16"),""),"") | H8: =IFERROR(D8*G8,0) -> 0 | I8: =IFERROR(F8*G8,0) -> 0 | L8: GROSS SALES | T8: =IFERROR(SUM(H4:H33),"") -> 0 | AA8: =IFERROR(SWITCH(C8,"Fixed Markup",INDIRECT("'"&B8&"'!$Q$14"),"Markup %",INDIRECT("'"&B8&"'!$AB$14"),"Margin %",INDIRECT("'"&B8&"'!$AM$14"),"Manual",INDIRECT("'"&B8&"'!$AX$14"),""),"") | AB8: =AA8*G8 -> 0 | AC8: =H8-AB8 -> 0 | AD8: =E8*G8 -> 0
D9: =IFERROR(SWITCH(C9,"Fixed Markup",INDIRECT("'"&B9&"'!$Q$16"),"Markup %",INDIRECT("'"&B9&"'!$AB$16"),"Margin %",INDIRECT("'"&B9&"'!$AM$16"),"Manual",INDIRECT("'"&B9&"'!$AX$11"),""),"") | E9: =IFERROR(INDIRECT("'"&B9&"'!$V$7"),"") | F9: =IFERROR(SWITCH(C9,"Fixed Markup",INDIRECT("'"&B9&"'!$P$17"),"Markup %",INDIRECT("'"&B9&"'!$AA$17"),"Margin %",INDIRECT("'"&B9&"'!$AL$17"),"Manual",INDIRECT("'"&B9&"'!$AW$16"),""),"") | H9: =IFERROR(D9*G9,0) -> 0 | I9: =IFERROR(F9*G9,0) -> 0 | L9: Less: VAT | T9: =-SUM(AB5:AB498) -> 0 | AA9: =IFERROR(SWITCH(C9,"Fixed Markup",INDIRECT("'"&B9&"'!$Q$14"),"Markup %",INDIRECT("'"&B9&"'!$AB$14"),"Margin %",INDIRECT("'"&B9&"'!$AM$14"),"Manual",INDIRECT("'"&B9&"'!$AX$14"),""),"") | AB9: =AA9*G9 -> 0 | AC9: =H9-AB9 -> 0 | AD9: =E9*G9 -> 0
D10: =IFERROR(SWITCH(C10,"Fixed Markup",INDIRECT("'"&B10&"'!$Q$16"),"Markup %",INDIRECT("'"&B10&"'!$AB$16"),"Margin %",INDIRECT("'"&B10&"'!$AM$16"),"Manual",INDIRECT("'"&B10&"'!$AX$11"),""),"") | E10: =IFERROR(INDIRECT("'"&B10&"'!$V$7"),"") | F10: =IFERROR(SWITCH(C10,"Fixed Markup",INDIRECT("'"&B10&"'!$P$17"),"Markup %",INDIRECT("'"&B10&"'!$AA$17"),"Margin %",INDIRECT("'"&B10&"'!$AL$17"),"Manual",INDIRECT("'"&B10&"'!$AW$16"),""),"") | H10: =IFERROR(D10*G10,0) -> 0 | I10: =IFERROR(F10*G10,0) -> 0 | AA10: =IFERROR(SWITCH(C10,"Fixed Markup",INDIRECT("'"&B10&"'!$Q$14"),"Markup %",INDIRECT("'"&B10&"'!$AB$14"),"Margin %",INDIRECT("'"&B10&"'!$AM$14"),"Manual",INDIRECT("'"&B10&"'!$AX$14"),""),"") | AB10: =AA10*G10 -> 0 | AC10: =H10-AB10 -> 0 | AD10: =E10*G10 -> 0
D11: =IFERROR(SWITCH(C11,"Fixed Markup",INDIRECT("'"&B11&"'!$Q$16"),"Markup %",INDIRECT("'"&B11&"'!$AB$16"),"Margin %",INDIRECT("'"&B11&"'!$AM$16"),"Manual",INDIRECT("'"&B11&"'!$AX$11"),""),"") | E11: =IFERROR(INDIRECT("'"&B11&"'!$V$7"),"") | F11: =IFERROR(SWITCH(C11,"Fixed Markup",INDIRECT("'"&B11&"'!$P$17"),"Markup %",INDIRECT("'"&B11&"'!$AA$17"),"Margin %",INDIRECT("'"&B11&"'!$AL$17"),"Manual",INDIRECT("'"&B11&"'!$AW$16"),""),"") | H11: =IFERROR(D11*G11,0) -> 0 | I11: =IFERROR(F11*G11,0) -> 0 | L11: NET SALES | T11: =SUM(T8:X9) -> 0 | AA11: =IFERROR(SWITCH(C11,"Fixed Markup",INDIRECT("'"&B11&"'!$Q$14"),"Markup %",INDIRECT("'"&B11&"'!$AB$14"),"Margin %",INDIRECT("'"&B11&"'!$AM$14"),"Manual",INDIRECT("'"&B11&"'!$AX$14"),""),"") | AB11: =AA11*G11 -> 0 | AC11: =H11-AB11 -> 0 | AD11: =E11*G11 -> 0
D12: =IFERROR(SWITCH(C12,"Fixed Markup",INDIRECT("'"&B12&"'!$Q$16"),"Markup %",INDIRECT("'"&B12&"'!$AB$16"),"Margin %",INDIRECT("'"&B12&"'!$AM$16"),"Manual",INDIRECT("'"&B12&"'!$AX$11"),""),"") | E12: =IFERROR(INDIRECT("'"&B12&"'!$V$7"),"") | F12: =IFERROR(SWITCH(C12,"Fixed Markup",INDIRECT("'"&B12&"'!$P$17"),"Markup %",INDIRECT("'"&B12&"'!$AA$17"),"Margin %",INDIRECT("'"&B12&"'!$AL$17"),"Manual",INDIRECT("'"&B12&"'!$AW$16"),""),"") | H12: =IFERROR(D12*G12,0) -> 0 | I12: =IFERROR(F12*G12,0) -> 0 | L12: Less: Cost of Goods Sold | T12: =-IFERROR(SUMPRODUCT(E5:E98,G5:G98),"") -> 0 | AA12: =IFERROR(SWITCH(C12,"Fixed Markup",INDIRECT("'"&B12&"'!$Q$14"),"Markup %",INDIRECT("'"&B12&"'!$AB$14"),"Margin %",INDIRECT("'"&B12&"'!$AM$14"),"Manual",INDIRECT("'"&B12&"'!$AX$14"),""),"") | AB12: =AA12*G12 -> 0 | AC12: =H12-AB12 -> 0 | AD12: =E12*G12 -> 0
D13: =IFERROR(SWITCH(C13,"Fixed Markup",INDIRECT("'"&B13&"'!$Q$16"),"Markup %",INDIRECT("'"&B13&"'!$AB$16"),"Margin %",INDIRECT("'"&B13&"'!$AM$16"),"Manual",INDIRECT("'"&B13&"'!$AX$11"),""),"") | E13: =IFERROR(INDIRECT("'"&B13&"'!$V$7"),"") | F13: =IFERROR(SWITCH(C13,"Fixed Markup",INDIRECT("'"&B13&"'!$P$17"),"Markup %",INDIRECT("'"&B13&"'!$AA$17"),"Margin %",INDIRECT("'"&B13&"'!$AL$17"),"Manual",INDIRECT("'"&B13&"'!$AW$16"),""),"") | H13: =IFERROR(D13*G13,0) -> 0 | I13: =IFERROR(F13*G13,0) -> 0 | AA13: =IFERROR(SWITCH(C13,"Fixed Markup",INDIRECT("'"&B13&"'!$Q$14"),"Markup %",INDIRECT("'"&B13&"'!$AB$14"),"Margin %",INDIRECT("'"&B13&"'!$AM$14"),"Manual",INDIRECT("'"&B13&"'!$AX$14"),""),"") | AB13: =AA13*G13 -> 0 | AC13: =H13-AB13 -> 0 | AD13: =E13*G13 -> 0
D14: =IFERROR(SWITCH(C14,"Fixed Markup",INDIRECT("'"&B14&"'!$Q$16"),"Markup %",INDIRECT("'"&B14&"'!$AB$16"),"Margin %",INDIRECT("'"&B14&"'!$AM$16"),"Manual",INDIRECT("'"&B14&"'!$AX$11"),""),"") | E14: =IFERROR(INDIRECT("'"&B14&"'!$V$7"),"") | F14: =IFERROR(SWITCH(C14,"Fixed Markup",INDIRECT("'"&B14&"'!$P$17"),"Markup %",INDIRECT("'"&B14&"'!$AA$17"),"Margin %",INDIRECT("'"&B14&"'!$AL$17"),"Manual",INDIRECT("'"&B14&"'!$AW$16"),""),"") | H14: =IFERROR(D14*G14,0) -> 0 | I14: =IFERROR(F14*G14,0) -> 0 | L14: GROSS PROFIT | T14: =SUM(T11:X12) -> 0 | AA14: =IFERROR(SWITCH(C14,"Fixed Markup",INDIRECT("'"&B14&"'!$Q$14"),"Markup %",INDIRECT("'"&B14&"'!$AB$14"),"Margin %",INDIRECT("'"&B14&"'!$AM$14"),"Manual",INDIRECT("'"&B14&"'!$AX$14"),""),"") | AB14: =AA14*G14 -> 0 | AC14: =H14-AB14 -> 0 | AD14: =E14*G14 -> 0
D15: =IFERROR(SWITCH(C15,"Fixed Markup",INDIRECT("'"&B15&"'!$Q$16"),"Markup %",INDIRECT("'"&B15&"'!$AB$16"),"Margin %",INDIRECT("'"&B15&"'!$AM$16"),"Manual",INDIRECT("'"&B15&"'!$AX$11"),""),"") | E15: =IFERROR(INDIRECT("'"&B15&"'!$V$7"),"") | F15: =IFERROR(SWITCH(C15,"Fixed Markup",INDIRECT("'"&B15&"'!$P$17"),"Markup %",INDIRECT("'"&B15&"'!$AA$17"),"Margin %",INDIRECT("'"&B15&"'!$AL$17"),"Manual",INDIRECT("'"&B15&"'!$AW$16"),""),"") | H15: =IFERROR(D15*G15,0) -> 0 | I15: =IFERROR(F15*G15,0) -> 0 | L15: Less Monthly OPEX | T15: =-OPEX!C25 -> 0 | AA15: =IFERROR(SWITCH(C15,"Fixed Markup",INDIRECT("'"&B15&"'!$Q$14"),"Markup %",INDIRECT("'"&B15&"'!$AB$14"),"Margin %",INDIRECT("'"&B15&"'!$AM$14"),"Manual",INDIRECT("'"&B15&"'!$AX$14"),""),"") | AB15: =AA15*G15 -> 0 | AC15: =H15-AB15 -> 0 | AD15: =E15*G15 -> 0
D16: =IFERROR(SWITCH(C16,"Fixed Markup",INDIRECT("'"&B16&"'!$Q$16"),"Markup %",INDIRECT("'"&B16&"'!$AB$16"),"Margin %",INDIRECT("'"&B16&"'!$AM$16"),"Manual",INDIRECT("'"&B16&"'!$AX$11"),""),"") | E16: =IFERROR(INDIRECT("'"&B16&"'!$V$7"),"") | F16: =IFERROR(SWITCH(C16,"Fixed Markup",INDIRECT("'"&B16&"'!$P$17"),"Markup %",INDIRECT("'"&B16&"'!$AA$17"),"Margin %",INDIRECT("'"&B16&"'!$AL$17"),"Manual",INDIRECT("'"&B16&"'!$AW$16"),""),"") | H16: =IFERROR(D16*G16,0) -> 0 | I16: =IFERROR(F16*G16,0) -> 0 | AA16: =IFERROR(SWITCH(C16,"Fixed Markup",INDIRECT("'"&B16&"'!$Q$14"),"Markup %",INDIRECT("'"&B16&"'!$AB$14"),"Margin %",INDIRECT("'"&B16&"'!$AM$14"),"Manual",INDIRECT("'"&B16&"'!$AX$14"),""),"") | AB16: =AA16*G16 -> 0 | AC16: =H16-AB16 -> 0 | AD16: =E16*G16 -> 0
D17: =IFERROR(SWITCH(C17,"Fixed Markup",INDIRECT("'"&B17&"'!$Q$16"),"Markup %",INDIRECT("'"&B17&"'!$AB$16"),"Margin %",INDIRECT("'"&B17&"'!$AM$16"),"Manual",INDIRECT("'"&B17&"'!$AX$11"),""),"") | E17: =IFERROR(INDIRECT("'"&B17&"'!$V$7"),"") | F17: =IFERROR(SWITCH(C17,"Fixed Markup",INDIRECT("'"&B17&"'!$P$17"),"Markup %",INDIRECT("'"&B17&"'!$AA$17"),"Margin %",INDIRECT("'"&B17&"'!$AL$17"),"Manual",INDIRECT("'"&B17&"'!$AW$16"),""),"") | H17: =IFERROR(D17*G17,0) -> 0 | I17: =IFERROR(F17*G17,0) -> 0 | L17: NET PROFIT | T17: =T14+T15 -> 0 | AA17: =IFERROR(SWITCH(C17,"Fixed Markup",INDIRECT("'"&B17&"'!$Q$14"),"Markup %",INDIRECT("'"&B17&"'!$AB$14"),"Margin %",INDIRECT("'"&B17&"'!$AM$14"),"Manual",INDIRECT("'"&B17&"'!$AX$14"),""),"") | AB17: =AA17*G17 -> 0 | AC17: =H17-AB17 -> 0 | AD17: =E17*G17 -> 0
D18: =IFERROR(SWITCH(C18,"Fixed Markup",INDIRECT("'"&B18&"'!$Q$16"),"Markup %",INDIRECT("'"&B18&"'!$AB$16"),"Margin %",INDIRECT("'"&B18&"'!$AM$16"),"Manual",INDIRECT("'"&B18&"'!$AX$11"),""),"") | E18: =IFERROR(INDIRECT("'"&B18&"'!$V$7"),"") | F18: =IFERROR(SWITCH(C18,"Fixed Markup",INDIRECT("'"&B18&"'!$P$17"),"Markup %",INDIRECT("'"&B18&"'!$AA$17"),"Margin %",INDIRECT("'"&B18&"'!$AL$17"),"Manual",INDIRECT("'"&B18&"'!$AW$16"),""),"") | H18: =IFERROR(D18*G18,0) -> 0 | I18: =IFERROR(F18*G18,0) -> 0 | L18: Net Profit Margin | T18: =IFERROR(T17/T11,0) -> 0 | AA18: =IFERROR(SWITCH(C18,"Fixed Markup",INDIRECT("'"&B18&"'!$Q$14"),"Markup %",INDIRECT("'"&B18&"'!$AB$14"),"Margin %",INDIRECT("'"&B18&"'!$AM$14"),"Manual",INDIRECT("'"&B18&"'!$AX$14"),""),"") | AB18: =AA18*G18 -> 0 | AC18: =H18-AB18 -> 0 | AD18: =E18*G18 -> 0
D19: =IFERROR(SWITCH(C19,"Fixed Markup",INDIRECT("'"&B19&"'!$Q$16"),"Markup %",INDIRECT("'"&B19&"'!$AB$16"),"Margin %",INDIRECT("'"&B19&"'!$AM$16"),"Manual",INDIRECT("'"&B19&"'!$AX$11"),""),"") | E19: =IFERROR(INDIRECT("'"&B19&"'!$V$7"),"") | F19: =IFERROR(SWITCH(C19,"Fixed Markup",INDIRECT("'"&B19&"'!$P$17"),"Markup %",INDIRECT("'"&B19&"'!$AA$17"),"Margin %",INDIRECT("'"&B19&"'!$AL$17"),"Manual",INDIRECT("'"&B19&"'!$AW$16"),""),"") | H19: =IFERROR(D19*G19,0) -> 0 | I19: =IFERROR(F19*G19,0) -> 0 | AA19: =IFERROR(SWITCH(C19,"Fixed Markup",INDIRECT("'"&B19&"'!$Q$14"),"Markup %",INDIRECT("'"&B19&"'!$AB$14"),"Margin %",INDIRECT("'"&B19&"'!$AM$14"),"Manual",INDIRECT("'"&B19&"'!$AX$14"),""),"") | AB19: =AA19*G19 -> 0 | AC19: =H19-AB19 -> 0 | AD19: =E19*G19 -> 0
D20: =IFERROR(SWITCH(C20,"Fixed Markup",INDIRECT("'"&B20&"'!$Q$16"),"Markup %",INDIRECT("'"&B20&"'!$AB$16"),"Margin %",INDIRECT("'"&B20&"'!$AM$16"),"Manual",INDIRECT("'"&B20&"'!$AX$11"),""),"") | E20: =IFERROR(INDIRECT("'"&B20&"'!$V$7"),"") | F20: =IFERROR(SWITCH(C20,"Fixed Markup",INDIRECT("'"&B20&"'!$P$17"),"Markup %",INDIRECT("'"&B20&"'!$AA$17"),"Margin %",INDIRECT("'"&B20&"'!$AL$17"),"Manual",INDIRECT("'"&B20&"'!$AW$16"),""),"") | H20: =IFERROR(D20*G20,0) -> 0 | I20: =IFERROR(F20*G20,0) -> 0 | L20: For planning purposes only | AA20: =IFERROR(SWITCH(C20,"Fixed Markup",INDIRECT("'"&B20&"'!$Q$14"),"Markup %",INDIRECT("'"&B20&"'!$AB$14"),"Margin %",INDIRECT("'"&B20&"'!$AM$14"),"Manual",INDIRECT("'"&B20&"'!$AX$14"),""),"") | AB20: =AA20*G20 -> 0 | AC20: =H20-AB20 -> 0 | AD20: =E20*G20 -> 0
D21: =IFERROR(SWITCH(C21,"Fixed Markup",INDIRECT("'"&B21&"'!$Q$16"),"Markup %",INDIRECT("'"&B21&"'!$AB$16"),"Margin %",INDIRECT("'"&B21&"'!$AM$16"),"Manual",INDIRECT("'"&B21&"'!$AX$11"),""),"") | E21: =IFERROR(INDIRECT("'"&B21&"'!$V$7"),"") | F21: =IFERROR(SWITCH(C21,"Fixed Markup",INDIRECT("'"&B21&"'!$P$17"),"Markup %",INDIRECT("'"&B21&"'!$AA$17"),"Margin %",INDIRECT("'"&B21&"'!$AL$17"),"Manual",INDIRECT("'"&B21&"'!$AW$16"),""),"") | H21: =IFERROR(D21*G21,0) -> 0 | I21: =IFERROR(F21*G21,0) -> 0 | AA21: =IFERROR(SWITCH(C21,"Fixed Markup",INDIRECT("'"&B21&"'!$Q$14"),"Markup %",INDIRECT("'"&B21&"'!$AB$14"),"Margin %",INDIRECT("'"&B21&"'!$AM$14"),"Manual",INDIRECT("'"&B21&"'!$AX$14"),""),"") | AB21: =AA21*G21 -> 0 | AC21: =H21-AB21 -> 0 | AD21: =E21*G21 -> 0
D22: =IFERROR(SWITCH(C22,"Fixed Markup",INDIRECT("'"&B22&"'!$Q$16"),"Markup %",INDIRECT("'"&B22&"'!$AB$16"),"Margin %",INDIRECT("'"&B22&"'!$AM$16"),"Manual",INDIRECT("'"&B22&"'!$AX$11"),""),"") | E22: =IFERROR(INDIRECT("'"&B22&"'!$V$7"),"") | F22: =IFERROR(SWITCH(C22,"Fixed Markup",INDIRECT("'"&B22&"'!$P$17"),"Markup %",INDIRECT("'"&B22&"'!$AA$17"),"Margin %",INDIRECT("'"&B22&"'!$AL$17"),"Manual",INDIRECT("'"&B22&"'!$AW$16"),""),"") | H22: =IFERROR(D22*G22,0) -> 0 | I22: =IFERROR(F22*G22,0) -> 0 | L22: This is a projection based on your recipes, selling prioces, expected monthly orders, and OPEX. It does NOT represent your actual busines results. Use it to test different sales scenarios and see if your expected monthly sales can cover your operating expenses and generate a profit. | AA22: =IFERROR(SWITCH(C22,"Fixed Markup",INDIRECT("'"&B22&"'!$Q$14"),"Markup %",INDIRECT("'"&B22&"'!$AB$14"),"Margin %",INDIRECT("'"&B22&"'!$AM$14"),"Manual",INDIRECT("'"&B22&"'!$AX$14"),""),"") | AB22: =AA22*G22 -> 0 | AC22: =H22-AB22 -> 0 | AD22: =E22*G22 -> 0
D23: =IFERROR(SWITCH(C23,"Fixed Markup",INDIRECT("'"&B23&"'!$Q$16"),"Markup %",INDIRECT("'"&B23&"'!$AB$16"),"Margin %",INDIRECT("'"&B23&"'!$AM$16"),"Manual",INDIRECT("'"&B23&"'!$AX$11"),""),"") | E23: =IFERROR(INDIRECT("'"&B23&"'!$V$7"),"") | F23: =IFERROR(SWITCH(C23,"Fixed Markup",INDIRECT("'"&B23&"'!$P$17"),"Markup %",INDIRECT("'"&B23&"'!$AA$17"),"Margin %",INDIRECT("'"&B23&"'!$AL$17"),"Manual",INDIRECT("'"&B23&"'!$AW$16"),""),"") | H23: =IFERROR(D23*G23,0) -> 0 | I23: =IFERROR(F23*G23,0) -> 0 | AA23: =IFERROR(SWITCH(C23,"Fixed Markup",INDIRECT("'"&B23&"'!$Q$14"),"Markup %",INDIRECT("'"&B23&"'!$AB$14"),"Margin %",INDIRECT("'"&B23&"'!$AM$14"),"Manual",INDIRECT("'"&B23&"'!$AX$14"),""),"") | AB23: =AA23*G23 -> 0 | AC23: =H23-AB23 -> 0 | AD23: =E23*G23 -> 0
D24: =IFERROR(SWITCH(C24,"Fixed Markup",INDIRECT("'"&B24&"'!$Q$16"),"Markup %",INDIRECT("'"&B24&"'!$AB$16"),"Margin %",INDIRECT("'"&B24&"'!$AM$16"),"Manual",INDIRECT("'"&B24&"'!$AX$11"),""),"") | E24: =IFERROR(INDIRECT("'"&B24&"'!$V$7"),"") | F24: =IFERROR(SWITCH(C24,"Fixed Markup",INDIRECT("'"&B24&"'!$P$17"),"Markup %",INDIRECT("'"&B24&"'!$AA$17"),"Margin %",INDIRECT("'"&B24&"'!$AL$17"),"Manual",INDIRECT("'"&B24&"'!$AW$16"),""),"") | H24: =IFERROR(D24*G24,0) -> 0 | I24: =IFERROR(F24*G24,0) -> 0 | AA24: =IFERROR(SWITCH(C24,"Fixed Markup",INDIRECT("'"&B24&"'!$Q$14"),"Markup %",INDIRECT("'"&B24&"'!$AB$14"),"Margin %",INDIRECT("'"&B24&"'!$AM$14"),"Manual",INDIRECT("'"&B24&"'!$AX$14"),""),"") | AB24: =AA24*G24 -> 0 | AC24: =H24-AB24 -> 0 | AD24: =E24*G24 -> 0
D25: =IFERROR(SWITCH(C25,"Fixed Markup",INDIRECT("'"&B25&"'!$Q$16"),"Markup %",INDIRECT("'"&B25&"'!$AB$16"),"Margin %",INDIRECT("'"&B25&"'!$AM$16"),"Manual",INDIRECT("'"&B25&"'!$AX$11"),""),"") | E25: =IFERROR(INDIRECT("'"&B25&"'!$V$7"),"") | F25: =IFERROR(SWITCH(C25,"Fixed Markup",INDIRECT("'"&B25&"'!$P$17"),"Markup %",INDIRECT("'"&B25&"'!$AA$17"),"Margin %",INDIRECT("'"&B25&"'!$AL$17"),"Manual",INDIRECT("'"&B25&"'!$AW$16"),""),"") | H25: =IFERROR(D25*G25,0) -> 0 | I25: =IFERROR(F25*G25,0) -> 0 | AA25: =IFERROR(SWITCH(C25,"Fixed Markup",INDIRECT("'"&B25&"'!$Q$14"),"Markup %",INDIRECT("'"&B25&"'!$AB$14"),"Margin %",INDIRECT("'"&B25&"'!$AM$14"),"Manual",INDIRECT("'"&B25&"'!$AX$14"),""),"") | AB25: =AA25*G25 -> 0 | AC25: =H25-AB25 -> 0 | AD25: =E25*G25 -> 0
D26: =IFERROR(SWITCH(C26,"Fixed Markup",INDIRECT("'"&B26&"'!$Q$16"),"Markup %",INDIRECT("'"&B26&"'!$AB$16"),"Margin %",INDIRECT("'"&B26&"'!$AM$16"),"Manual",INDIRECT("'"&B26&"'!$AX$11"),""),"") | E26: =IFERROR(INDIRECT("'"&B26&"'!$V$7"),"") | F26: =IFERROR(SWITCH(C26,"Fixed Markup",INDIRECT("'"&B26&"'!$P$17"),"Markup %",INDIRECT("'"&B26&"'!$AA$17"),"Margin %",INDIRECT("'"&B26&"'!$AL$17"),"Manual",INDIRECT("'"&B26&"'!$AW$16"),""),"") | H26: =IFERROR(D26*G26,0) -> 0 | I26: =IFERROR(F26*G26,0) -> 0 | AA26: =IFERROR(SWITCH(C26,"Fixed Markup",INDIRECT("'"&B26&"'!$Q$14"),"Markup %",INDIRECT("'"&B26&"'!$AB$14"),"Margin %",INDIRECT("'"&B26&"'!$AM$14"),"Manual",INDIRECT("'"&B26&"'!$AX$14"),""),"") | AB26: =AA26*G26 -> 0 | AC26: =H26-AB26 -> 0 | AD26: =E26*G26 -> 0
D27: =IFERROR(SWITCH(C27,"Fixed Markup",INDIRECT("'"&B27&"'!$Q$16"),"Markup %",INDIRECT("'"&B27&"'!$AB$16"),"Margin %",INDIRECT("'"&B27&"'!$AM$16"),"Manual",INDIRECT("'"&B27&"'!$AX$11"),""),"") | E27: =IFERROR(INDIRECT("'"&B27&"'!$V$7"),"") | F27: =IFERROR(SWITCH(C27,"Fixed Markup",INDIRECT("'"&B27&"'!$P$17"),"Markup %",INDIRECT("'"&B27&"'!$AA$17"),"Margin %",INDIRECT("'"&B27&"'!$AL$17"),"Manual",INDIRECT("'"&B27&"'!$AW$16"),""),"") | H27: =IFERROR(D27*G27,0) -> 0 | I27: =IFERROR(F27*G27,0) -> 0 | AA27: =IFERROR(SWITCH(C27,"Fixed Markup",INDIRECT("'"&B27&"'!$Q$14"),"Markup %",INDIRECT("'"&B27&"'!$AB$14"),"Margin %",INDIRECT("'"&B27&"'!$AM$14"),"Manual",INDIRECT("'"&B27&"'!$AX$14"),""),"") | AB27: =AA27*G27 -> 0 | AC27: =H27-AB27 -> 0 | AD27: =E27*G27 -> 0
D28: =IFERROR(SWITCH(C28,"Fixed Markup",INDIRECT("'"&B28&"'!$Q$16"),"Markup %",INDIRECT("'"&B28&"'!$AB$16"),"Margin %",INDIRECT("'"&B28&"'!$AM$16"),"Manual",INDIRECT("'"&B28&"'!$AX$11"),""),"") | E28: =IFERROR(INDIRECT("'"&B28&"'!$V$7"),"") | F28: =IFERROR(SWITCH(C28,"Fixed Markup",INDIRECT("'"&B28&"'!$P$17"),"Markup %",INDIRECT("'"&B28&"'!$AA$17"),"Margin %",INDIRECT("'"&B28&"'!$AL$17"),"Manual",INDIRECT("'"&B28&"'!$AW$16"),""),"") | H28: =IFERROR(D28*G28,0) -> 0 | I28: =IFERROR(F28*G28,0) -> 0 | AA28: =IFERROR(SWITCH(C28,"Fixed Markup",INDIRECT("'"&B28&"'!$Q$14"),"Markup %",INDIRECT("'"&B28&"'!$AB$14"),"Margin %",INDIRECT("'"&B28&"'!$AM$14"),"Manual",INDIRECT("'"&B28&"'!$AX$14"),""),"") | AB28: =AA28*G28 -> 0 | AC28: =H28-AB28 -> 0 | AD28: =E28*G28 -> 0
D29: =IFERROR(SWITCH(C29,"Fixed Markup",INDIRECT("'"&B29&"'!$Q$16"),"Markup %",INDIRECT("'"&B29&"'!$AB$16"),"Margin %",INDIRECT("'"&B29&"'!$AM$16"),"Manual",INDIRECT("'"&B29&"'!$AX$11"),""),"") | E29: =IFERROR(INDIRECT("'"&B29&"'!$V$7"),"") | F29: =IFERROR(SWITCH(C29,"Fixed Markup",INDIRECT("'"&B29&"'!$P$17"),"Markup %",INDIRECT("'"&B29&"'!$AA$17"),"Margin %",INDIRECT("'"&B29&"'!$AL$17"),"Manual",INDIRECT("'"&B29&"'!$AW$16"),""),"") | H29: =IFERROR(D29*G29,0) -> 0 | I29: =IFERROR(F29*G29,0) -> 0 | AA29: =IFERROR(SWITCH(C29,"Fixed Markup",INDIRECT("'"&B29&"'!$Q$14"),"Markup %",INDIRECT("'"&B29&"'!$AB$14"),"Margin %",INDIRECT("'"&B29&"'!$AM$14"),"Manual",INDIRECT("'"&B29&"'!$AX$14"),""),"") | AB29: =AA29*G29 -> 0 | AC29: =H29-AB29 -> 0 | AD29: =E29*G29 -> 0
D30: =IFERROR(SWITCH(C30,"Fixed Markup",INDIRECT("'"&B30&"'!$Q$16"),"Markup %",INDIRECT("'"&B30&"'!$AB$16"),"Margin %",INDIRECT("'"&B30&"'!$AM$16"),"Manual",INDIRECT("'"&B30&"'!$AX$11"),""),"") | E30: =IFERROR(INDIRECT("'"&B30&"'!$V$7"),"") | F30: =IFERROR(SWITCH(C30,"Fixed Markup",INDIRECT("'"&B30&"'!$P$17"),"Markup %",INDIRECT("'"&B30&"'!$AA$17"),"Margin %",INDIRECT("'"&B30&"'!$AL$17"),"Manual",INDIRECT("'"&B30&"'!$AW$16"),""),"") | H30: =IFERROR(D30*G30,0) -> 0 | I30: =IFERROR(F30*G30,0) -> 0 | AA30: =IFERROR(SWITCH(C30,"Fixed Markup",INDIRECT("'"&B30&"'!$Q$14"),"Markup %",INDIRECT("'"&B30&"'!$AB$14"),"Margin %",INDIRECT("'"&B30&"'!$AM$14"),"Manual",INDIRECT("'"&B30&"'!$AX$14"),""),"") | AB30: =AA30*G30 -> 0 | AC30: =H30-AB30 -> 0 | AD30: =E30*G30 -> 0
D31: =IFERROR(SWITCH(C31,"Fixed Markup",INDIRECT("'"&B31&"'!$Q$16"),"Markup %",INDIRECT("'"&B31&"'!$AB$16"),"Margin %",INDIRECT("'"&B31&"'!$AM$16"),"Manual",INDIRECT("'"&B31&"'!$AX$11"),""),"") | E31: =IFERROR(INDIRECT("'"&B31&"'!$V$7"),"") | F31: =IFERROR(SWITCH(C31,"Fixed Markup",INDIRECT("'"&B31&"'!$P$17"),"Markup %",INDIRECT("'"&B31&"'!$AA$17"),"Margin %",INDIRECT("'"&B31&"'!$AL$17"),"Manual",INDIRECT("'"&B31&"'!$AW$16"),""),"") | H31: =IFERROR(D31*G31,0) -> 0 | I31: =IFERROR(F31*G31,0) -> 0 | AA31: =IFERROR(SWITCH(C31,"Fixed Markup",INDIRECT("'"&B31&"'!$Q$14"),"Markup %",INDIRECT("'"&B31&"'!$AB$14"),"Margin %",INDIRECT("'"&B31&"'!$AM$14"),"Manual",INDIRECT("'"&B31&"'!$AX$14"),""),"") | AB31: =AA31*G31 -> 0 | AC31: =H31-AB31 -> 0 | AD31: =E31*G31 -> 0
D32: =IFERROR(SWITCH(C32,"Fixed Markup",INDIRECT("'"&B32&"'!$Q$16"),"Markup %",INDIRECT("'"&B32&"'!$AB$16"),"Margin %",INDIRECT("'"&B32&"'!$AM$16"),"Manual",INDIRECT("'"&B32&"'!$AX$11"),""),"") | E32: =IFERROR(INDIRECT("'"&B32&"'!$V$7"),"") | F32: =IFERROR(SWITCH(C32,"Fixed Markup",INDIRECT("'"&B32&"'!$P$17"),"Markup %",INDIRECT("'"&B32&"'!$AA$17"),"Margin %",INDIRECT("'"&B32&"'!$AL$17"),"Manual",INDIRECT("'"&B32&"'!$AW$16"),""),"") | H32: =IFERROR(D32*G32,0) -> 0 | I32: =IFERROR(F32*G32,0) -> 0 | AA32: =IFERROR(SWITCH(C32,"Fixed Markup",INDIRECT("'"&B32&"'!$Q$14"),"Markup %",INDIRECT("'"&B32&"'!$AB$14"),"Margin %",INDIRECT("'"&B32&"'!$AM$14"),"Manual",INDIRECT("'"&B32&"'!$AX$14"),""),"") | AB32: =AA32*G32 -> 0 | AC32: =H32-AB32 -> 0 | AD32: =E32*G32 -> 0
D33: =IFERROR(SWITCH(C33,"Fixed Markup",INDIRECT("'"&B33&"'!$Q$16"),"Markup %",INDIRECT("'"&B33&"'!$AB$16"),"Margin %",INDIRECT("'"&B33&"'!$AM$16"),"Manual",INDIRECT("'"&B33&"'!$AX$11"),""),"") | E33: =IFERROR(INDIRECT("'"&B33&"'!$V$7"),"") | F33: =IFERROR(SWITCH(C33,"Fixed Markup",INDIRECT("'"&B33&"'!$P$17"),"Markup %",INDIRECT("'"&B33&"'!$AA$17"),"Margin %",INDIRECT("'"&B33&"'!$AL$17"),"Manual",INDIRECT("'"&B33&"'!$AW$16"),""),"") | H33: =IFERROR(D33*G33,0) -> 0 | I33: =IFERROR(F33*G33,0) -> 0 | AA33: =IFERROR(SWITCH(C33,"Fixed Markup",INDIRECT("'"&B33&"'!$Q$14"),"Markup %",INDIRECT("'"&B33&"'!$AB$14"),"Margin %",INDIRECT("'"&B33&"'!$AM$14"),"Manual",INDIRECT("'"&B33&"'!$AX$14"),""),"") | AB33: =AA33*G33 -> 0 | AC33: =H33-AB33 -> 0 | AD33: =E33*G33 -> 0
D34: =IFERROR(SWITCH(C34,"Fixed Markup",INDIRECT("'"&B34&"'!$Q$16"),"Markup %",INDIRECT("'"&B34&"'!$AB$16"),"Margin %",INDIRECT("'"&B34&"'!$AM$16"),"Manual",INDIRECT("'"&B34&"'!$AX$11"),""),"") | E34: =IFERROR(INDIRECT("'"&B34&"'!$V$7"),"") | F34: =IFERROR(SWITCH(C34,"Fixed Markup",INDIRECT("'"&B34&"'!$P$17"),"Markup %",INDIRECT("'"&B34&"'!$AA$17"),"Margin %",INDIRECT("'"&B34&"'!$AL$17"),"Manual",INDIRECT("'"&B34&"'!$AW$16"),""),"") | H34: =IFERROR(D34*G34,0) -> 0 | I34: =IFERROR(F34*G34,0) -> 0 | AA34: =IFERROR(SWITCH(C34,"Fixed Markup",INDIRECT("'"&B34&"'!$Q$14"),"Markup %",INDIRECT("'"&B34&"'!$AB$14"),"Margin %",INDIRECT("'"&B34&"'!$AM$14"),"Manual",INDIRECT("'"&B34&"'!$AX$14"),""),"") | AB34: =AA34*G34 -> 0 | AC34: =H34-AB34 -> 0 | AD34: =E34*G34 -> 0
... D498: =IFERROR(SWITCH(C498,"Fixed Markup",INDIRECT("'"&B498&"'!$Q$16"),"Markup %",INDIRECT("'"&B498&"'!$AB$16"),"Margin %",INDIRECT("'"&B498&"'!$AM$16"),"Manual",INDIRECT("'"&B498&"'!$AX$11"),""),"") | E498: =IFERROR(INDIRECT("'"&B498&"'!$V$7"),"") | F498: =IFERROR(SWITCH(C498,"Fixed Markup",INDIRECT("'"&B498&"'!$P$17"),"Markup %",INDIRECT("'"&B498&"'!$AA$17"),"Margin %",INDIRECT("'"&B498&"'!$AL$17"),"Manual",INDIRECT("'"&B498&"'!$AW$16"),""),"") | H498: =IFERROR(D498*G498,0) -> 0 | I498: =IFERROR(F498*G498,0) -> 0 | AA498: =IFERROR(SWITCH(C498,"Fixed Markup",INDIRECT("'"&B498&"'!$Q$14"),"Markup %",INDIRECT("'"&B498&"'!$AB$14"),"Margin %",INDIRECT("'"&B498&"'!$AM$14"),"Manual",INDIRECT("'"&B498&"'!$AX$14"),""),"") | AB498: =AA498*G498 -> 0 | AC498: =H498-AB498 -> 0 | AD498: =E498*G498 -> 0

Sheet Blank Recipe DUPLICATE THIS
B3: RECIPE NAME | R3: Batch | V3: Serving | AA3: OTHER SETTINGS
L5: Total ingredient cost | R5: =IF(AG5, IF($G$20>1, SUM($Q$27:$T$292), "")/(1-AG6),IF($G$20>1, SUM($Q$27:$T$292), "")) -> 0 | V5: =IF(AG5, (SUM(Q27:T292)/$G$20)/(1-AG6),SUM(Q27:T292)/$G$20) -> 0 | AB5: Include wastage? | AG5: TRUE
L6: Total packaging cost | R6: =IF(AG5, IF($G$20>1, SUM(AL27:AO292), "")/(1-AG6),IF($G$20>1, SUM(AL27:AO292), "")) -> 0 | V6: =IF(AG5,(SUM(AL27:AO292)/$G$20)/(1-AG6),SUM(AL27:AO292)/$G$20) -> 0 | AB6: Wastage % | AG6: 0.05
L7: Total cost | R7: =R5+R6 -> 0 | V7: =V5+V6 -> 0
L11: Fixed markup | W11: Markup % | AH11: Margin % | AS11: Selling price
L13: Price before VAT | Q13: =$V$7+Q11 -> 0 | W13: Price before VAT | AB13: =$V$7*(1+AB11) -> 0 | AH13: Price before VAT | AM13: =$V$7/(1-AM11) -> 0 | AS13: Price before VAT | AX13: =IF(G18,AX11/(1+G19),AX11) -> 0
L14: VAT | Q14: =IF($G$18,Q13*$G$19,0) -> 0 | W14: VAT | AB14: =IF($G$18,AB13*$G$19,0) -> 0 | AH14: VAT | AM14: =IF($G$18,AM13*$G$19,0) -> 0 | AS14: VAT | AX14: =AX11-AX13 -> 0
AS15: Cost per order | AX15: =V7 -> 0
B16: SETTINGS | L16: Selling price | Q16: =Q13+Q14 -> 0 | W16: Selling price | AB16: =AB13+AB14 -> 0 | AH16: Selling price | AM16: =AM13+AM14 -> 0 | AT16: Profit | AW16: =AX13-AX15 -> 0
M17: Profit | P17: =Q13-V7 -> 0 | X17: Profit | AA17: =AB13-V7 -> 0 | AI17: Profit | AL17: =AM13-V7 -> 0
C18: Include VAT? | G18: TRUE | AS18: Implied margin % | AX18: =IFERROR((AX13-$V$7)/AX13,"")
C19: VAT% | G19: 0.12 | L19: Discount amount | Q19: =Q13*$G$22 -> 0 | W19: Discount amount | AB19: =AB13*$G$22 -> 0 | AH19: Discount amount | AM19: =AM13*$G$22 -> 0 | AS19: Implied markup % | AX19: =IFERROR((AX13-AX15)/AX15,"")
C20: # of Servings | G20: 1 | L20: Discounted price | Q20: =Q13-Q19 -> 0 | W20: Discounted price | AB20: =AB13-AB19 -> 0 | AH20: Discounted price | AM20: =AM13-AM19 -> 0
C21: PWD/senior discount % | M21: Profit | P21: =Q20-$V$7 -> 0 | X21: Profit | AA21: =AB20-$V$7 -> 0 | AI21: Profit | AL21: =AM20-$V$7 -> 0 | AS21: Discount amount | AX21: =AX13*$G$22 -> 0
G22: 0.2 | AS22: Discounted price | AX22: =AX13-AX21 -> 0
AT23: Profit | AW23: =AX22-$V$7 -> 0
B26: INGREDIENTS | G26: QTY | J26: UNIT | M26: UNIT COST | Q26: COST | W26: ITEM | AB26: QTY | AE26: UNIT | AH26: UNIT COST | AL26: COST
J27: {=IF(B27="","", INDEX(Ingredients!G:G, MATCH(B27, Ingredients!B:B,0)))} | M27: {=IF(B27="","", INDEX(Ingredients!H:H, MATCH(B27, Ingredients!B:B,0)))} | Q27: =IF(G27="","", G27*M27) | AE27: {=IF(W27="","", INDEX(Other!G:G, MATCH(W27, Other!B:B,0)))} | AH27: {=IF(W27="","", INDEX(Other!H:H, MATCH(W27, Other!B:B,0)))} | AL27: =IF(AB27="","", AB27*AH27) | AR27: IMPORTANT!!!
J28: {=IF(B28="","", INDEX(Ingredients!G:G, MATCH(B28, Ingredients!B:B,0)))} | M28: {=IF(B28="","", INDEX(Ingredients!H:H, MATCH(B28, Ingredients!B:B,0)))} | Q28: =IF(G28="","", G28*M28) | AE28: {=IF(W28="","", INDEX(Other!G:G, MATCH(W28, Other!B:B,0)))} | AH28: {=IF(W28="","", INDEX(Other!H:H, MATCH(W28, Other!B:B,0)))} | AL28: =IF(AB28="","", AB28*AH28) | AR28: <- Please do not add or delete rows, as this may break the formulas. Only replace the existing values.
J29: {=IF(B29="","", INDEX(Ingredients!G:G, MATCH(B29, Ingredients!B:B,0)))} | M29: {=IF(B29="","", INDEX(Ingredients!H:H, MATCH(B29, Ingredients!B:B,0)))} | Q29: =IF(G29="","", G29*M29) | AE29: {=IF(W29="","", INDEX(Other!G:G, MATCH(W29, Other!B:B,0)))} | AH29: {=IF(W29="","", INDEX(Other!H:H, MATCH(W29, Other!B:B,0)))} | AL29: =IF(AB29="","", AB29*AH29)
J30: {=IF(B30="","", INDEX(Ingredients!G:G, MATCH(B30, Ingredients!B:B,0)))} | M30: {=IF(B30="","", INDEX(Ingredients!H:H, MATCH(B30, Ingredients!B:B,0)))} | Q30: =IF(G30="","", G30*M30) | AE30: {=IF(W30="","", INDEX(Other!G:G, MATCH(W30, Other!B:B,0)))} | AH30: {=IF(W30="","", INDEX(Other!H:H, MATCH(W30, Other!B:B,0)))} | AL30: =IF(AB30="","", AB30*AH30)
J31: {=IF(B31="","", INDEX(Ingredients!G:G, MATCH(B31, Ingredients!B:B,0)))} | M31: {=IF(B31="","", INDEX(Ingredients!H:H, MATCH(B31, Ingredients!B:B,0)))} | Q31: =IF(G31="","", G31*M31) | AE31: {=IF(W31="","", INDEX(Other!G:G, MATCH(W31, Other!B:B,0)))} | AH31: {=IF(W31="","", INDEX(Other!H:H, MATCH(W31, Other!B:B,0)))} | AL31: =IF(AB31="","", AB31*AH31)
J32: {=IF(B32="","", INDEX(Ingredients!G:G, MATCH(B32, Ingredients!B:B,0)))} | M32: {=IF(B32="","", INDEX(Ingredients!H:H, MATCH(B32, Ingredients!B:B,0)))} | Q32: =IF(G32="","", G32*M32) | AE32: {=IF(W32="","", INDEX(Other!G:G, MATCH(W32, Other!B:B,0)))} | AH32: {=IF(W32="","", INDEX(Other!H:H, MATCH(W32, Other!B:B,0)))} | AL32: =IF(AB32="","", AB32*AH32)
J33: {=IF(B33="","", INDEX(Ingredients!G:G, MATCH(B33, Ingredients!B:B,0)))} | M33: {=IF(B33="","", INDEX(Ingredients!H:H, MATCH(B33, Ingredients!B:B,0)))} | Q33: =IF(G33="","", G33*M33) | AE33: {=IF(W33="","", INDEX(Other!G:G, MATCH(W33, Other!B:B,0)))} | AH33: {=IF(W33="","", INDEX(Other!H:H, MATCH(W33, Other!B:B,0)))} | AL33: =IF(AB33="","", AB33*AH33)
J34: {=IF(B34="","", INDEX(Ingredients!G:G, MATCH(B34, Ingredients!B:B,0)))} | M34: {=IF(B34="","", INDEX(Ingredients!H:H, MATCH(B34, Ingredients!B:B,0)))} | Q34: =IF(G34="","", G34*M34) | AE34: {=IF(W34="","", INDEX(Other!G:G, MATCH(W34, Other!B:B,0)))} | AH34: {=IF(W34="","", INDEX(Other!H:H, MATCH(W34, Other!B:B,0)))} | AL34: =IF(AB34="","", AB34*AH34)
J35: {=IF(B35="","", INDEX(Ingredients!G:G, MATCH(B35, Ingredients!B:B,0)))} | M35: {=IF(B35="","", INDEX(Ingredients!H:H, MATCH(B35, Ingredients!B:B,0)))} | Q35: =IF(G35="","", G35*M35) | AE35: {=IF(W35="","", INDEX(Other!G:G, MATCH(W35, Other!B:B,0)))} | AH35: {=IF(W35="","", INDEX(Other!H:H, MATCH(W35, Other!B:B,0)))} | AL35: =IF(AB35="","", AB35*AH35)
J36: {=IF(B36="","", INDEX(Ingredients!G:G, MATCH(B36, Ingredients!B:B,0)))} | M36: {=IF(B36="","", INDEX(Ingredients!H:H, MATCH(B36, Ingredients!B:B,0)))} | Q36: =IF(G36="","", G36*M36) | AE36: {=IF(W36="","", INDEX(Other!G:G, MATCH(W36, Other!B:B,0)))} | AH36: {=IF(W36="","", INDEX(Other!H:H, MATCH(W36, Other!B:B,0)))} | AL36: =IF(AB36="","", AB36*AH36)
J37: {=IF(B37="","", INDEX(Ingredients!G:G, MATCH(B37, Ingredients!B:B,0)))} | M37: {=IF(B37="","", INDEX(Ingredients!H:H, MATCH(B37, Ingredients!B:B,0)))} | Q37: =IF(G37="","", G37*M37) | AE37: {=IF(W37="","", INDEX(Other!G:G, MATCH(W37, Other!B:B,0)))} | AH37: {=IF(W37="","", INDEX(Other!H:H, MATCH(W37, Other!B:B,0)))} | AL37: =IF(AB37="","", AB37*AH37)
J38: {=IF(B38="","", INDEX(Ingredients!G:G, MATCH(B38, Ingredients!B:B,0)))} | M38: {=IF(B38="","", INDEX(Ingredients!H:H, MATCH(B38, Ingredients!B:B,0)))} | Q38: =IF(G38="","", G38*M38) | AE38: {=IF(W38="","", INDEX(Other!G:G, MATCH(W38, Other!B:B,0)))} | AH38: {=IF(W38="","", INDEX(Other!H:H, MATCH(W38, Other!B:B,0)))} | AL38: =IF(AB38="","", AB38*AH38)
J39: {=IF(B39="","", INDEX(Ingredients!G:G, MATCH(B39, Ingredients!B:B,0)))} | M39: {=IF(B39="","", INDEX(Ingredients!H:H, MATCH(B39, Ingredients!B:B,0)))} | Q39: =IF(G39="","", G39*M39) | AE39: {=IF(W39="","", INDEX(Other!G:G, MATCH(W39, Other!B:B,0)))} | AH39: {=IF(W39="","", INDEX(Other!H:H, MATCH(W39, Other!B:B,0)))} | AL39: =IF(AB39="","", AB39*AH39)
J40: {=IF(B40="","", INDEX(Ingredients!G:G, MATCH(B40, Ingredients!B:B,0)))} | M40: {=IF(B40="","", INDEX(Ingredients!H:H, MATCH(B40, Ingredients!B:B,0)))} | Q40: =IF(G40="","", G40*M40) | AE40: {=IF(W40="","", INDEX(Other!G:G, MATCH(W40, Other!B:B,0)))} | AH40: {=IF(W40="","", INDEX(Other!H:H, MATCH(W40, Other!B:B,0)))} | AL40: =IF(AB40="","", AB40*AH40)
... J292: {=IF(B292="","", INDEX(Ingredients!G:G, MATCH(B292, Ingredients!B:B,0)))} | M292: {=IF(B292="","", INDEX(Ingredients!H:H, MATCH(B292, Ingredients!B:B,0)))} | Q292: =IF(G292="","", G292*M292) | AE292: {=IF(W292="","", INDEX(Other!G:G, MATCH(W292, Other!B:B,0)))} | AH292: {=IF(W292="","", INDEX(Other!H:H, MATCH(W292, Other!B:B,0)))} | AL292: =IF(AB292="","", AB292*AH292)
BB293: PROPERTY NOTICE: Original Food Costing Calculator created by JQ for PH Business Network (PBN). © 2026. Not for unauthorized reproduction, resale, redistribution, or removal of attribution.
